{
  "collapse-filter": false,
  "search": "",
  "showTags": true,
  "showAttachments": false,
  "hideUnresolved": false,
  "showOrphans": true,
  "collapse-color-groups": false,
  "colorGroups": [
    {
      "query": "tag:#afte-effects  ",
      "color": {
        "a": 1,
        "rgb": 14701138
      }
    }
  ],
  "collapse-display": false,
  "showArrow": false,
  "textFadeMultiplier": 1.4,
  "nodeSizeMultiplier": 1.76842447916667,
  "lineSizeMultiplier": 1,
  "collapse-forces": true,
  "centerStrength": 0.4002685546875,
  "repelStrength": 10,
  "linkStrength": 1,
  "linkDistance": 30,
  "scale": 1.7707575131323625,
  "close": false
}